setup.py
bin/bragi
bragi/__init__.py
bragi/cpp_generator.py
bragi/parser.py
bragi/tokens.py
bragi/types.py
bragi/wireshark_generator.py
bragi.egg-info/PKG-INFO
bragi.egg-info/SOURCES.txt
bragi.egg-info/dependency_links.txt
bragi.egg-info/requires.txt
bragi.egg-info/top_level.txt