Metadata-Version: 2.2
Name: bragi
Version: 0.7
Home-page: https://github.com/managarm/bragi
Author: The Managarm Project
Author-email: info@managarm.org
License: MIT
Requires-Dist: lark-parser
Dynamic: author
Dynamic: author-email
Dynamic: home-page
Dynamic: license
Dynamic: requires-dist
